rdial/__init__.py
rdial/_version.py
rdial/cmdline.py
rdial/config
rdial/events.py
rdial/utils.py
rdial-1.2.1.dist-info/COPYING
rdial-1.2.1.dist-info/METADATA
rdial-1.2.1.dist-info/WHEEL
rdial-1.2.1.dist-info/entry_points.txt
rdial-1.2.1.dist-info/top_level.txt
rdial-1.2.1.dist-info/zip-safe
rdial-1.2.1.dist-info/RECORD
