Metadata-Version: 2.1
Name: rdial
Version: 1.2.1
Summary: Minimal time tracking for maximal benefit
Home-page: https://github.com/JNRowe/rdial
Author: James Rowe
Author-email: jnrowe@gmail.com
License: GPL-3
Project-URL: Contributors, https://github.com/JNRowe/rdial/contributors/
Project-URL: Documentation, https://rdial.readthedocs.io/
Project-URL: Git repository, https://github.com/JNRowe/rdial/
Project-URL: Issue tracker, https://github.com/JNRowe/rdial/issues/
Keywords: timetracking,task,report
Platform: UNKNOWN
Classifier: Development Status :: 5 - Production/Stable
Classifier: Environment :: Console
Classifier: Intended Audience :: Developers
Classifier: Intended Audience :: End Users/Desktop
Classifier: Intended Audience :: Other Audience
Classifier: Intended Audience :: System Administrators
Classifier: License :: OSI Approved
Classifier: License :: OSI Approved :: GNU General Public License (GPL)
Classifier: License :: OSI Approved :: GNU General Public License v3 or later (GPLv3+)
Classifier: Natural Language :: English
Classifier: Operating System :: OS Independent
Classifier: Programming Language :: Python
Classifier: Programming Language :: Python :: 3
Classifier: Programming Language :: Python :: 3.6
Classifier: Programming Language :: Python :: 3.7
Classifier: Programming Language :: Python :: 3 :: Only
Classifier: Topic :: Office/Business
Classifier: Topic :: Office/Business :: News/Diary
Classifier: Topic :: Office/Business :: Scheduling
Classifier: Topic :: Other/Nonlisted Topic
Classifier: Topic :: Utilities
Requires-Dist: click (>=7.0)
Requires-Dist: jnrbase[iso_8601,colour] (>=1.1.0)
Requires-Dist: tabulate (>=0.8.2)
Requires-Dist: importlib-resources (>=1.0.2) ; python_version < "3.7"
